sencrop_olympus_library/__init__.py
sencrop_olympus_library/metrics/__init__.py
sencrop_olympus_library/metrics/metrics.py
sencrop_olympus_library/metrics/units.py
sencrop_olympus_library-0.1.0.dist-info/WHEEL
sencrop_olympus_library-0.1.0.dist-info/METADATA
sencrop_olympus_library-0.1.0.dist-info/RECORD
